fh_chat/__init__.py
fh_chat/src/__init__.py
fh_chat/src/chat.py
fh_chat/src/clients.py
fh_chat/src/stream_clients.py
fh_chat/src/ui.py
src/__init__.py
src/chat.py
src/clients.py
fh_chat-0.3.1.dist-info/LICENSE
fh_chat-0.3.1.dist-info/METADATA
fh_chat-0.3.1.dist-info/WHEEL
fh_chat-0.3.1.dist-info/top_level.txt
fh_chat-0.3.1.dist-info/RECORD
