Metadata-Version: 2.1
Name: fh-chat
Version: 0.3.1
Summary: A package for chat functionality in FastHTML.
Home-page: https://github.com/rian-dolphin/fasthtml-chat
Author: Rian Dolphin
License: MIT
Classifier: Programming Language :: Python :: 3
Classifier: License :: OSI Approved :: MIT License
Classifier: Operating System :: OS Independent
Requires-Python: >=3.8
License-File: LICENSE
Requires-Dist: python-fasthtml >=0.4.4
Provides-Extra: dev
Requires-Dist: twine ; extra == 'dev'
